pandoc_gui/__init__.py
pandoc_gui/__main__.py
pandoc_gui/gui.py
pandoc_gui-1.0.5.dist-info/licenses/LICENSE
pandoc_gui-1.0.5.dist-info/METADATA
pandoc_gui-1.0.5.dist-info/WHEEL
pandoc_gui-1.0.5.dist-info/entry_points.txt
pandoc_gui-1.0.5.dist-info/top_level.txt
pandoc_gui-1.0.5.dist-info/RECORD
