Metadata-Version: 2.4
Name: pandoc_gui
Version: 1.0.5
Summary: A Universal Pandoc GUI Converter
Home-page: https://github.com/jtao/pandoc_gui
Author: Jian Tao
Author-email: jtao@tamu.edu
Classifier: Programming Language :: Python :: 3
Classifier: License :: OSI Approved :: MIT License
Classifier: Operating System :: OS Independent
Requires-Python: >=3.12
License-File: LICENSE
Dynamic: author
Dynamic: author-email
Dynamic: classifier
Dynamic: description
Dynamic: description-content-type
Dynamic: home-page
Dynamic: license-file
Dynamic: requires-python
Dynamic: summary
